machine_shop/__init__.py
machine_shop/adapters/__init__.py
machine_shop/adapters/anth.py
machine_shop/adapters/coh_native.py
machine_shop/adapters/gem_native.py
machine_shop/adapters/gem_rest.py
machine_shop/adapters/grq_native.py
machine_shop/adapters/grq_rest.py
machine_shop/adapters/oai_native.py
machine_shop/adapters/oai_rest.py
machine_shop/adapters/plm_rest.py
machine_shop/util/__init__.py
machine_shop/util/xml_tags.py
machine_shop-0.0.2.dist-info/LICENSE
machine_shop-0.0.2.dist-info/METADATA
machine_shop-0.0.2.dist-info/WHEEL
machine_shop-0.0.2.dist-info/top_level.txt
machine_shop-0.0.2.dist-info/RECORD
