Metadata-Version: 2.1
Name: machine-shop
Version: 0.0.2
Summary: The tool sets and tools for individual types of machines
Author-email: Alexander Fedotov <alex.fedotov@aol.com>
Project-URL: Homepage, https://github.com/meta-machina/machine-shop
Project-URL: Bug Tracker, https://github.com/meta-machina/machine-shop/issues
Classifier: Programming Language :: Python :: 3
Classifier: License :: OSI Approved :: MIT License
Classifier: Operating System :: OS Independent
Requires-Python: >=3.10
License-File: LICENSE
